bugcount.py
bugcount-0.0.11.dist-info/METADATA
bugcount-0.0.11.dist-info/WHEEL
bugcount-0.0.11.dist-info/entry_points.txt
bugcount-0.0.11.dist-info/top_level.txt
bugcount-0.0.11.dist-info/RECORD
