Metadata-Version: 2.1
Name: bugcount
Version: 0.0.11
Summary: A package for counting BLOB objects
Home-page: https://github.com/y-takefuji/counting-for-entomologists
Author: yoshiyasu takefuji
Author-email: takefuji@keio.jp
License: UNKNOWN
Project-URL: Bug Tracker, https://github.com/y-takefuji/counting-for-entomologists
Platform: UNKNOWN
Classifier: Programming Language :: Python :: 3
Classifier: License :: OSI Approved :: MIT License
Classifier: Operating System :: OS Independent
Requires-Python: >=3.8
